balconyapp/__init__.py
balconyapp/example_app.py
balconyapp-0.1.0.dist-info/LICENSE
balconyapp-0.1.0.dist-info/WHEEL
balconyapp-0.1.0.dist-info/METADATA
balconyapp-0.1.0.dist-info/RECORD
